{
  "equipLevel": 3,
  "parts": [
    {
      "resKey": "angel_equip_1_3_p1",
      "target": "TRAIT",
      "isToken": false,
      "addOrOverrideTalentDataBundle": {
        "candidates": null
      },
      "overrideTraitDataBundle": {
        "candidates": [
          {
            "additionalDescription": "攻击空中单位时攻击力提升至<@ba.kw>{atk_scale:0%}</>",
            "unlockCondition": {
              "phase": 2,
              "level": 60
            },
            "requiredPotentialRank": 0,
            "blackboard": [
              {
                "key": "atk_scale",
                "value": 1.1
              }
            ],
            "overrideDescripton": null,
            "prefabKey": null,
            "rangeId": null
          }
        ]
      }
    },
    {
      "resKey": "angel_equip_1_3_p2",
      "target": "TALENT",
      "isToken": false,
      "addOrOverrideTalentDataBundle": {
        "candidates": [
          {
            "displayRangeId": false,
            "upgradeDescription": "攻击力+8%，生命上限+14%。置入战场后这个效果会同样赋予给两名随机友方单位",
            "talentIndex": 1,
            "unlockCondition": {
              "phase": 2,
              "level": 60
            },
            "requiredPotentialRank": 0,
            "prefabKey": "2",
            "name": "天使的祝福",
            "description": null,
            "rangeId": null,
            "blackboard": [
              {
                "key": "atk",
                "value": 0.08
              },
              {
                "key": "max_hp",
                "value": 0.14
              }
            ]
          },
          {
            "displayRangeId": false,
            "upgradeDescription": "攻击力+10%<@ba.talpu>（+2%）</>，生命上限+17%<@ba.talpu>（+3%）</>。置入战场后这个效果会同样赋予给两名随机友方单位",
            "talentIndex": 1,
            "unlockCondition": {
              "phase": 2,
              "level": 60
            },
            "requiredPotentialRank": 5,
            "prefabKey": "2",
            "name": "天使的祝福",
            "description": null,
            "rangeId": null,
            "blackboard": [
              {
                "key": "atk",
                "value": 0.1
              },
              {
                "key": "max_hp",
                "value": 0.17
              }
            ]
          }
        ]
      },
      "overrideTraitDataBundle": {
        "candidates": null
      }
    }
  ],
  "attributeBlackboard": [
    {
      "key": "max_hp",
      "value": 190.0
    },
    {
      "key": "atk",
      "value": 41.0
    }
  ],
  "tokenAttributeBlackboard": {}
}