{
  "equipLevel": 3,
  "parts": [
    {
      "resKey": "nearl2_equip_1_3_p1",
      "target": "TRAIT",
      "isToken": false,
      "addOrOverrideTalentDataBundle": {
        "candidates": null
      },
      "overrideTraitDataBundle": {
        "candidates": [
          {
            "additionalDescription": "攻击被阻挡的敌人时攻击力提升至<@ba.vup>{atk_scale:0%}</>",
            "unlockCondition": {
              "phase": 2,
              "level": 60
            },
            "requiredPotentialRank": 0,
            "blackboard": [
              {
                "key": "atk_scale",
                "value": 1.15
              }
            ],
            "overrideDescripton": null,
            "prefabKey": null,
            "rangeId": null
          }
        ]
      }
    },
    {
      "resKey": "token_nearl2_equip_1_3_p1",
      "target": "TRAIT",
      "isToken": true,
      "addOrOverrideTalentDataBundle": {
        "candidates": null
      },
      "overrideTraitDataBundle": {
        "candidates": [
          {
            "additionalDescription": null,
            "unlockCondition": {
              "phase": 2,
              "level": 60
            },
            "requiredPotentialRank": 0,
            "blackboard": [
              {
                "key": "atk_scale",
                "value": 1.15
              }
            ],
            "overrideDescripton": null,
            "prefabKey": null,
            "rangeId": null
          }
        ]
      }
    },
    {
      "resKey": null,
      "target": "TALENT_DATA_ONLY",
      "isToken": false,
      "addOrOverrideTalentDataBundle": {
        "candidates": [
          {
            "displayRangeId": false,
            "upgradeDescription": "攻击无视敌人28%的防御力",
            "talentIndex": 1,
            "unlockCondition": {
              "phase": 2,
              "level": 60
            },
            "requiredPotentialRank": 0,
            "prefabKey": "2",
            "name": "破晓",
            "description": null,
            "rangeId": null,
            "blackboard": [
              {
                "key": "def_penetrate",
                "value": 0.28
              }
            ]
          },
          {
            "displayRangeId": false,
            "upgradeDescription": "攻击无视敌人31%<@ba.talpu>（+3%）</>的防御力",
            "talentIndex": 1,
            "unlockCondition": {
              "phase": 2,
              "level": 60
            },
            "requiredPotentialRank": 4,
            "prefabKey": "2",
            "name": "破晓",
            "description": null,
            "rangeId": null,
            "blackboard": [
              {
                "key": "def_penetrate",
                "value": 0.31
              }
            ]
          }
        ]
      },
      "overrideTraitDataBundle": {
        "candidates": null
      }
    }
  ],
  "attributeBlackboard": [
    {
      "key": "max_hp",
      "value": 330.0
    },
    {
      "key": "atk",
      "value": 105.0
    }
  ],
  "tokenAttributeBlackboard": {}
}