{
  "enemy_name": "enemy_1240_ltgint",
  "level": [
    {
      "level": 0,
      "enemyData": {
        "name": {
          "m_defined": true,
          "m_value": "量产巨像"
        },
        "description": {
          "m_defined": true,
          "m_value": "<@eb.key>阻挡能力大于等于2</>的作战人员可以阻止；处于重整束流上时，防御和法术抗性大幅下降"
        },
        "prefabKey": {
          "m_defined": true,
          "m_value": "enemy_1240_ltgint"
        },
        "attributes": {
          "maxHp": {
            "m_defined": true,
            "m_value": 15000
          },
          "atk": {
            "m_defined": true,
            "m_value": 650
          },
          "def": {
            "m_defined": true,
            "m_value": 1200
          },
          "magicResistance": {
            "m_defined": true,
            "m_value": 50.0
          },
          "cost": {
            "m_defined": false,
            "m_value": 0
          },
          "blockCnt": {
            "m_defined": false,
            "m_value": 0
          },
          "moveSpeed": {
            "m_defined": true,
            "m_value": 0.75
          },
          "attackSpeed": {
            "m_defined": true,
            "m_value": 100.0
          },
          "baseAttackTime": {
            "m_defined": true,
            "m_value": 4.0
          },
          "respawnTime": {
            "m_defined": false,
            "m_value": 0
          },
          "hpRecoveryPerSec": {
            "m_defined": false,
            "m_value": 0.0
          },
          "spRecoveryPerSec": {
            "m_defined": false,
            "m_value": 0.0
          },
          "maxDeployCount": {
            "m_defined": false,
            "m_value": 0
          },
          "massLevel": {
            "m_defined": true,
            "m_value": 4
          },
          "baseForceLevel": {
            "m_defined": false,
            "m_value": 0
          },
          "tauntLevel": {
            "m_defined": false,
            "m_value": 0
          },
          "stunImmune": {
            "m_defined": true,
            "m_value": false
          },
          "silenceImmune": {
            "m_defined": false,
            "m_value": false
          },
          "sleepImmune": {
            "m_defined": true,
            "m_value": true
          },
          "frozenImmune": {
            "m_defined": false,
            "m_value": false
          },
          "levitateImmune": {
            "m_defined": false,
            "m_value": false
          }
        },
        "lifePointReduce": {
          "m_defined": true,
          "m_value": 1
        },
        "levelType": {
          "m_defined": true,
          "m_value": 1
        },
        "rangeRadius": {
          "m_defined": false,
          "m_value": 0.0
        },
        "numOfExtraDrops": {
          "m_defined": false,
          "m_value": 0
        },
        "talentBlackboard": [
          {
            "key": "Weak.def",
            "value": -1000.0,
            "valueStr": null
          },
          {
            "key": "Weak.magic_resistance",
            "value": -50.0,
            "valueStr": null
          }
        ],
        "skills": null,
        "spData": null
      }
    }
  ]
}
