{
  "enemy_name": "enemy_1085_sotiwz",
  "level": [
    {
      "level": 0,
      "enemyData": {
        "name": {
          "m_defined": true,
          "m_value": "游击队萨卡兹术师"
        },
        "description": {
          "m_defined": true,
          "m_value": "周期性对周围单位造成相当于攻击力的法术伤害。接触脉冲波时，<@eb.key>不受伤害</>且攻击<@eb.key>范围扩大</>"
        },
        "prefabKey": {
          "m_defined": true,
          "m_value": "enemy_1085_sotiwz"
        },
        "attributes": {
          "maxHp": {
            "m_defined": true,
            "m_value": 7000
          },
          "atk": {
            "m_defined": true,
            "m_value": 350
          },
          "def": {
            "m_defined": true,
            "m_value": 400
          },
          "magicResistance": {
            "m_defined": true,
            "m_value": 50.0
          },
          "cost": {
            "m_defined": false,
            "m_value": 0
          },
          "blockCnt": {
            "m_defined": false,
            "m_value": 0
          },
          "moveSpeed": {
            "m_defined": true,
            "m_value": 0.75
          },
          "attackSpeed": {
            "m_defined": true,
            "m_value": 100.0
          },
          "baseAttackTime": {
            "m_defined": true,
            "m_value": 0.1
          },
          "respawnTime": {
            "m_defined": false,
            "m_value": 0
          },
          "hpRecoveryPerSec": {
            "m_defined": false,
            "m_value": 0.0
          },
          "spRecoveryPerSec": {
            "m_defined": false,
            "m_value": 0.0
          },
          "maxDeployCount": {
            "m_defined": false,
            "m_value": 0
          },
          "massLevel": {
            "m_defined": true,
            "m_value": 2
          },
          "baseForceLevel": {
            "m_defined": false,
            "m_value": 0
          },
          "tauntLevel": {
            "m_defined": false,
            "m_value": 0
          },
          "stunImmune": {
            "m_defined": false,
            "m_value": false
          },
          "silenceImmune": {
            "m_defined": true,
            "m_value": true
          },
          "sleepImmune": {
            "m_defined": false,
            "m_value": false
          },
          "frozenImmune": {
            "m_defined": false,
            "m_value": false
          },
          "levitateImmune": {
            "m_defined": false,
            "m_value": false
          }
        },
        "lifePointReduce": {
          "m_defined": true,
          "m_value": 1
        },
        "levelType": {
          "m_defined": true,
          "m_value": 1
        },
        "rangeRadius": {
          "m_defined": false,
          "m_value": 0.0
        },
        "numOfExtraDrops": {
          "m_defined": false,
          "m_value": 0
        },
        "talentBlackboard": null,
        "skills": [
          {
            "prefabKey": "Immo",
            "priority": 0,
            "cooldown": 5.0,
            "initCooldown": 0.0,
            "spCost": 0,
            "blackboard": [
              {
                "key": "atk_scale",
                "value": 1.0,
                "valueStr": null
              }
            ]
          },
          {
            "prefabKey": "Immo[Rage]",
            "priority": 0,
            "cooldown": 5.0,
            "initCooldown": 0.0,
            "spCost": 0,
            "blackboard": [
              {
                "key": "atk_scale",
                "value": 1.0,
                "valueStr": null
              }
            ]
          }
        ],
        "spData": null
      }
    }
  ]
}