{
  "name": "闪灵",
  "profession": "MEDIC",
  "subProfessionId": "physician",
  "star": 6,
  "skills": [
    {
      "overridePrefabKey": null,
      "overrideTokenKey": null,
      "skillId": "skchr_shining_1"
    },
    {
      "overridePrefabKey": null,
      "overrideTokenKey": null,
      "skillId": "skchr_shining_2"
    },
    {
      "overridePrefabKey": null,
      "overrideTokenKey": null,
      "skillId": "skchr_shining_3"
    }
  ],
  "elite": 2,
  "max_level": 90,
  "data": {
    "atk": 530,
    "attackSpeed": 100,
    "baseAttackTime": 2.85,
    "baseForceLevel": 0,
    "blockCnt": 1,
    "cost": 20,
    "def": 138,
    "frozenImmune": false,
    "hpRecoveryPerSec": 0,
    "levitateImmune": false,
    "magicResistance": 0,
    "massLevel": 0,
    "maxDeckStackCnt": 0,
    "maxDeployCount": 1,
    "maxHp": 1613,
    "moveSpeed": 1,
    "respawnTime": 70,
    "silenceImmune": false,
    "sleepImmune": false,
    "spRecoveryPerSec": 1,
    "stunImmune": false,
    "tauntLevel": 0
  },
  "teamId": "followers",
  "tokenKey": null,
  "trait": null
}
